reasoning_gym/__init__.py
reasoning_gym/composite.py
reasoning_gym/dataset.py
reasoning_gym/factory.py
reasoning_gym/utils.py
reasoning_gym/version_manager.py
reasoning_gym/algebra/__init__.py
reasoning_gym/algebra/complex_arithmetic.py
reasoning_gym/algebra/intermediate_integration.py
reasoning_gym/algebra/polynomial_equations.py
reasoning_gym/algebra/polynomial_multiplication.py
reasoning_gym/algebra/simple_equations.py
reasoning_gym/algebra/simple_integration.py
reasoning_gym/algorithmic/__init__.py
reasoning_gym/algorithmic/ab.py
reasoning_gym/algorithmic/base_conversion.py
reasoning_gym/algorithmic/binary_alternation.py
reasoning_gym/algorithmic/binary_matrix.py
reasoning_gym/algorithmic/caesar_cipher.py
reasoning_gym/algorithmic/count_primes.py
reasoning_gym/algorithmic/cryptarithm.py
reasoning_gym/algorithmic/game_of_life.py
reasoning_gym/algorithmic/game_of_life_halting.py
reasoning_gym/algorithmic/graph_color.py
reasoning_gym/algorithmic/group_anagrams.py
reasoning_gym/algorithmic/isomorphic_strings.py
reasoning_gym/algorithmic/jugs.py
reasoning_gym/algorithmic/letter_counting.py
reasoning_gym/algorithmic/letter_jumble.py
reasoning_gym/algorithmic/manipulate_matrix.py
reasoning_gym/algorithmic/number_filtering.py
reasoning_gym/algorithmic/number_sorting.py
reasoning_gym/algorithmic/palindrome_generation.py
reasoning_gym/algorithmic/palindrome_partitioning.py
reasoning_gym/algorithmic/pool_matrix.py
reasoning_gym/algorithmic/ransom_note.py
reasoning_gym/algorithmic/rotate_matrix.py
reasoning_gym/algorithmic/rotten_oranges.py
reasoning_gym/algorithmic/sentence_reordering.py
reasoning_gym/algorithmic/spell_backward.py
reasoning_gym/algorithmic/spiral_matrix.py
reasoning_gym/algorithmic/string_insertion.py
reasoning_gym/algorithmic/string_manipulation.py
reasoning_gym/algorithmic/string_splitting.py
reasoning_gym/algorithmic/string_synthesis.py
reasoning_gym/algorithmic/word_ladder.py
reasoning_gym/algorithmic/word_sequence_reversal.py
reasoning_gym-0.1.24.dist-info/METADATA
reasoning_gym-0.1.24.dist-info/WHEEL
reasoning_gym-0.1.24.dist-info/entry_points.txt
reasoning_gym-0.1.24.dist-info/licenses/LICENSE
reasoning_gym-0.1.24.dist-info/RECORD
