Metadata-Version: 2.4
Name: reasoning_gym
Version: 0.1.24
Summary: A library of procedural dataset generators for training reasoning models
Project-URL: Homepage, https://github.com/open-thought/reasoning-gym
Project-URL: Bug Tracker, https://github.com/open-thought/reasoning-gym/issues
Author-email: Open-Thought community <andreas.koepf@xamla.com>
License-Expression: Apache-2.0
License-File: LICENSE
Classifier: License :: OSI Approved :: Apache Software License
Classifier: Operating System :: OS Independent
Classifier: Programming Language :: Python :: 3
Requires-Python: >=3.10
Requires-Dist: arckit==0.1.0
Requires-Dist: bfi==1.0.4
Requires-Dist: cellpylib==2.4.0
Requires-Dist: magiccube==0.3.0
Requires-Dist: pycosat==0.6.6
Requires-Dist: pyfiglet==1.0.2
Requires-Dist: pytz>=2024.1
Requires-Dist: pyyaml>=6.0.2
Requires-Dist: sympy>=1.13.1
Requires-Dist: tabulate==0.9.0
Requires-Dist: zss>=1.2.0
Provides-Extra: cli
Requires-Dist: httpx>=0.27.0; extra == 'cli'
Requires-Dist: pyyaml>=6.0.1; extra == 'cli'
Requires-Dist: rich>=13.7.0; extra == 'cli'
Requires-Dist: typer>=0.9.0; extra == 'cli'
Provides-Extra: scripts
Requires-Dist: datasets>=3.5.0; extra == 'scripts'
Provides-Extra: server
Requires-Dist: fastapi>=0.109.0; extra == 'server'
Requires-Dist: pydantic-settings>=2.1.0; extra == 'server'
Requires-Dist: uvicorn>=0.27.0; extra == 'server'
Provides-Extra: test
Requires-Dist: httpx>=0.27.0; extra == 'test'
Requires-Dist: pytest-cov>=4.0.0; extra == 'test'
Requires-Dist: pytest>=7.0.0; extra == 'test'
